MANIFEST.in
setup.py
SloPOS.egg-info/PKG-INFO
SloPOS.egg-info/SOURCES.txt
SloPOS.egg-info/dependency_links.txt
SloPOS.egg-info/requires.txt
SloPOS.egg-info/top_level.txt
slopos/__init__.py
slopos/sl-tagger.pickle