Metadata-Version: 1.1
Name: SloPOS
Version: 1.0
Summary: Part of speech tagger for Slovenian (SI) language based on NLTK
Home-page: https://github.com/izacus/slo_pos
Author: Jernej Virag
Author-email: jernej@virag.si
License: LGPL
Platform: UNKNOWN
Classifier: License :: OSI Approved :: GNU Library or Lesser General Public License (LGPL)
Classifier: Operating System :: OS Independent
Classifier: Intended Audience :: Developers
Classifier: Topic :: Software Development :: Libraries :: Python Modules
Classifier: Programming Language :: Python
Classifier: Topic :: Text Processing :: Linguistic
